protocol_formatter/__init__.py
protocol_formatter/__main__.py
protocol_formatter-0.1.3.dist-info/licenses/LICENSE
protocol_formatter-0.1.3.dist-info/METADATA
protocol_formatter-0.1.3.dist-info/WHEEL
protocol_formatter-0.1.3.dist-info/entry_points.txt
protocol_formatter-0.1.3.dist-info/top_level.txt
protocol_formatter-0.1.3.dist-info/RECORD
