Metadata-Version: 2.4
Name: protocol_formatter
Version: 0.1.3
Summary: A utility to format raw text protocols into styled PDFs
Home-page: https://github.com/adhikaripb/protocol_formatter
Author: Prakash Babu Adhikari
Author-email: pbadhikari@yahoo.com
Classifier: Programming Language :: Python :: 3
Classifier: License :: OSI Approved :: MIT License
Classifier: Operating System :: OS Independent
Requires-Python: >=3.7
License-File: LICENSE
Requires-Dist: python-docx
Requires-Dist: fpdf
Requires-Dist: svgwrite
Requires-Dist: cairosvg
Dynamic: author
Dynamic: author-email
Dynamic: classifier
Dynamic: description
Dynamic: description-content-type
Dynamic: home-page
Dynamic: license-file
Dynamic: requires-dist
Dynamic: requires-python
Dynamic: summary
